{
	"id": "blog-post",
	"name": "Blog Post",
	"description": "", //TODO: fill this field
	"icon": "[place_your_url_here]/icon.png",
	"category": "applications",
	"developer": {
		"id": "echo",
		"name": "Echo",
		"url": "http://www.aboutecho.com",
		"email": "solutions@aboutecho.com",
		"icon": "http://cdn.echoenabled.com/images/echo.png"
	},
	"plans": [{
		"id": "unlimited",
		"name": "Unlimited plan"
	}],
	"dashboards": [{
		"id": "instances",
		"title": "Instances",
		"script": "[place_your_url_here]/dashboard.js",
		"component": "BlogPost.Dashboard"
	}],
	"application": {
		"component": "BlogPost",
		"script": "[place_your_url_here]/app.js"
	},
	"version": "0.1.0"
}
